docs/__init__.py
docs/conf.py
fake_factory-0.7.4.dist-info/DESCRIPTION.rst
fake_factory-0.7.4.dist-info/METADATA
fake_factory-0.7.4.dist-info/RECORD
fake_factory-0.7.4.dist-info/WHEEL
fake_factory-0.7.4.dist-info/entry_points.txt
fake_factory-0.7.4.dist-info/metadata.json
fake_factory-0.7.4.dist-info/pbr.json
fake_factory-0.7.4.dist-info/top_level.txt
fake_factory-0.7.4.dist-info/zip-safe
faker/__init__.py
faker/__main__.py
faker/build_docs.py
faker/cli.py
faker/config.py
faker/documentor.py
faker/factory.py
faker/generator.py
faker/providers/__init__.py
faker/providers/address/__init__.py
faker/providers/address/cs_CZ/__init__.py
faker/providers/address/de_DE/__init__.py
faker/providers/address/el_GR/__init__.py
faker/providers/address/en/__init__.py
faker/providers/address/en_AU/__init__.py
faker/providers/address/en_CA/__init__.py
faker/providers/address/en_GB/__init__.py
faker/providers/address/en_US/__init__.py
faker/providers/address/es/__init__.py
faker/providers/address/es_ES/__init__.py
faker/providers/address/es_MX/__init__.py
faker/providers/address/fa_IR/__init__.py
faker/providers/address/fi_FI/__init__.py
faker/providers/address/fr_CH/__init__.py
faker/providers/address/fr_FR/__init__.py
faker/providers/address/hi_IN/__init__.py
faker/providers/address/hr_HR/__init__.py
faker/providers/address/it_IT/__init__.py
faker/providers/address/ja_JP/__init__.py
faker/providers/address/ko_KR/__init__.py
faker/providers/address/ne_NP/__init__.py
faker/providers/address/nl_BE/__init__.py
faker/providers/address/nl_NL/__init__.py
faker/providers/address/no_NO/__init__.py
faker/providers/address/pl_PL/__init__.py
faker/providers/address/pt_BR/__init__.py
faker/providers/address/pt_PT/__init__.py
faker/providers/address/ru_RU/__init__.py
faker/providers/address/sk_SK/__init__.py
faker/providers/address/sl_SI/__init__.py
faker/providers/address/sv_SE/__init__.py
faker/providers/address/uk_UA/__init__.py
faker/providers/address/zh_CN/__init__.py
faker/providers/address/zh_TW/__init__.py
faker/providers/barcode/__init__.py
faker/providers/barcode/en_US/__init__.py
faker/providers/color/__init__.py
faker/providers/color/en_US/__init__.py
faker/providers/color/uk_UA/__init__.py
faker/providers/company/__init__.py
faker/providers/company/bg_BG/__init__.py
