Metadata-Version: 1.1
Name: fake-factory
Version: 0.7.4
Summary: Faker is a Python package that generates fake data for you.
Home-page: https://github.com/joke2k/faker
Author: joke2k
Author-email: joke2k@gmail.com
License: MIT License
Keywords: faker fixtures data test mock generator
Platform: any
Classifier: Development Status :: 3 - Alpha
Classifier: Environment :: Console
Classifier: Intended Audience :: Developers
Classifier: Programming Language :: Python
Classifier: Programming Language :: Python :: 2
Classifier: Programming Language :: Python :: 2.7
Classifier: Programming Language :: Python :: 3
Classifier: Programming Language :: Python :: 3.4
Classifier: Programming Language :: Python :: 3.5
Classifier: Topic :: Software Development :: Libraries :: Python Modules
Classifier: Topic :: Software Development :: Testing
Classifier: Topic :: Utilities
Classifier: License :: OSI Approved :: MIT License
